randomDateGenerator/__init__.py
randomDateGenerator/main.py
randomDateGenerator-0.1.0.dist-info/METADATA
randomDateGenerator-0.1.0.dist-info/WHEEL
randomDateGenerator-0.1.0.dist-info/top_level.txt
randomDateGenerator-0.1.0.dist-info/RECORD
